savant_rs-0.3.0.dist-info/METADATA
savant_rs-0.3.0.dist-info/WHEEL
savant_rs.libs/libsavant_core-0d0dbb77.so
savant_rs.libs/libsavant_core_py-8efa760e.so
savant_rs.libs/libstd-320ebc7037fb8f95-2c270c49.so
savant_rs/match_query/match_query.pyi
savant_rs/match_query/__init__.py
savant_rs/zmq/zmq.pyi
savant_rs/zmq/__init__.py
savant_rs/primitives/geometry/__init__.py
savant_rs/primitives/geometry/geometry.pyi
savant_rs/primitives/primitives.pyi
savant_rs/primitives/__init__.py
savant_rs/py.typed
savant_rs/savant_rs.pyi
savant_rs/include/savant_rs.h
savant_rs/logging/logging.pyi
savant_rs/logging/__init__.py
savant_rs/utils/utils.pyi
savant_rs/utils/__init__.py
savant_rs/__init__.py
savant_rs/draw_spec/draw_spec.pyi
savant_rs/draw_spec/__init__.py
savant_rs/savant_rs.cpython-311-x86_64-linux-gnu.so
savant_rs-0.3.0.dist-info/RECORD
